MANIFEST.in
README.rst
setup.cfg
setup.py
docs/HISTORY.rst
docs/INSTALL.txt
docs/LICENSE.GPL
docs/LICENSE.txt
src/collective/__init__.py
src/collective.blogging.egg-info/PKG-INFO
src/collective.blogging.egg-info/SOURCES.txt
src/collective.blogging.egg-info/dependency_links.txt
src/collective.blogging.egg-info/entry_points.txt
src/collective.blogging.egg-info/namespace_packages.txt
src/collective.blogging.egg-info/not-zip-safe
src/collective.blogging.egg-info/requires.txt
src/collective.blogging.egg-info/top_level.txt
src/collective/blogging/__init__.py
src/collective/blogging/configure.zcml
src/collective/blogging/content.zcml
src/collective/blogging/extenders.py
src/collective/blogging/handlers.py
src/collective/blogging/indexer.py
src/collective/blogging/interfaces.py
src/collective/blogging/migration.py
src/collective/blogging/nextprevious.py
src/collective/blogging/patch.py
src/collective/blogging/profiles.zcml
src/collective/blogging/setuphandlers.py
src/collective/blogging/sharing.py
src/collective/blogging/tests.py
src/collective/blogging/update_i18n.sh
src/collective/blogging/Extensions/Install.py
src/collective/blogging/Extensions/__init__.py
src/collective/blogging/actions/__init__.py
src/collective/blogging/actions/autoblog.py
src/collective/blogging/actions/configure.zcml
src/collective/blogging/browser/__init__.py
src/collective/blogging/browser/blog_macros.pt
src/collective/blogging/browser/bloggingview.py
src/collective/blogging/browser/blogview.pt
src/collective/blogging/browser/blogview.py
src/collective/blogging/browser/configure.zcml
src/collective/blogging/browser/document_byline.pt
src/collective/blogging/browser/document_byline.py
src/collective/blogging/browser/entry_macros.pt
src/collective/blogging/browser/entryview.pt
src/collective/blogging/browser/entryview.py
src/collective/blogging/browser/help.pt
src/collective/blogging/browser/help.py
src/collective/blogging/browser/keywords.pt
src/collective/blogging/browser/macros.py
src/collective/blogging/browser/sunburst.css
src/collective/blogging/browser/help_images/add_archive.png
src/collective/blogging/browser/help_images/add_portlet.png
src/collective/blogging/browser/help_images/archive_settings.png
src/collective/blogging/browser/help_images/blog_created.png
src/collective/blogging/browser/help_images/content_rule.png
