Metadata-Version: 2.1
Name: collective.blogging
Version: 1.4.0
Summary: A blogging extension for Plone 4.x.
Home-page: https://github.com/collective/collective.blogging
Author: Lukas Zdych
Author-email: lukas.zdych@gmail.com
License: GPL
Keywords: web plone blogging system extension cms
Platform: UNKNOWN
Classifier: Development Status :: 5 - Production/Stable
Classifier: Environment :: Web Environment
Classifier: Framework :: Plone :: 4.3
Classifier: Framework :: Plone
Classifier: Framework :: Zope2
Classifier: Framework :: Zope3
Classifier: Intended Audience :: Developers
Classifier: Intended Audience :: End Users/Desktop
Classifier: License :: OSI Approved :: GNU General Public License v2 (GPLv2)
Classifier: Operating System :: OS Independent
Classifier: Programming Language :: Python :: 2.7
Classifier: Programming Language :: Python
Classifier: Topic :: Internet
Classifier: Topic :: Software Development :: Libraries :: Python Modules
Provides-Extra: test
